AdaptivePELE/__init__.py
AdaptivePELE/setup.py
AdaptivePELE/AdaptivePELE/__init__.py
AdaptivePELE/AdaptivePELE/adaptiveSampling.py
AdaptivePELE/AdaptivePELE/automateRoundsAdaptive.py
AdaptivePELE/AdaptivePELE/makeRelease.py
AdaptivePELE/AdaptivePELE/runAllTests.py
AdaptivePELE/AdaptivePELE/analysis/__init__.py
AdaptivePELE/AdaptivePELE/analysis/addRejectedSteps.py
AdaptivePELE/AdaptivePELE/analysis/analyse.py
AdaptivePELE/AdaptivePELE/analysis/analyseClustering.py
AdaptivePELE/AdaptivePELE/analysis/backtrackAdaptiveTrajectory.py
AdaptivePELE/AdaptivePELE/analysis/compareClustering.py
AdaptivePELE/AdaptivePELE/analysis/convertTrajectory.py
AdaptivePELE/AdaptivePELE/analysis/correctRMSD.py
AdaptivePELE/AdaptivePELE/analysis/findfirstbindingevent.py
AdaptivePELE/AdaptivePELE/analysis/foldersFirstBindingEvent.py
AdaptivePELE/AdaptivePELE/analysis/histCM.py
AdaptivePELE/AdaptivePELE/analysis/makePNGs.py
AdaptivePELE/AdaptivePELE/analysis/networkCM.py
AdaptivePELE/AdaptivePELE/analysis/numberOfClusters.py
AdaptivePELE/AdaptivePELE/analysis/pathwayRMSD.py
AdaptivePELE/AdaptivePELE/analysis/plot3DNetwork.py
AdaptivePELE/AdaptivePELE/analysis/plotAdaptive.py
AdaptivePELE/AdaptivePELE/analysis/plotRMSF.py
AdaptivePELE/AdaptivePELE/analysis/plotSpawningClusters.py
AdaptivePELE/AdaptivePELE/analysis/splitTrajectory.py
AdaptivePELE/AdaptivePELE/analysis/writeClusteringStructures.py
AdaptivePELE/AdaptivePELE/analysis/writeNetworkFiles.py
AdaptivePELE/AdaptivePELE/analysis/writeTrajToSnapshot.py
AdaptivePELE/AdaptivePELE/atomset/__init__.py
AdaptivePELE/AdaptivePELE/atomset/setup.py
AdaptivePELE/AdaptivePELE/clustering/__init__.py
AdaptivePELE/AdaptivePELE/clustering/clustering.py
AdaptivePELE/AdaptivePELE/clustering/clusteringTypes.py
AdaptivePELE/AdaptivePELE/clustering/thresholdcalculator.py
AdaptivePELE/AdaptivePELE/clustering/thresholdcalculatortypes.py
AdaptivePELE/AdaptivePELE/constants/__init__.py
MSM_PELE-1.1.1.dist-info/DESCRIPTION.rst
MSM_PELE-1.1.1.dist-info/METADATA
MSM_PELE-1.1.1.dist-info/RECORD
MSM_PELE-1.1.1.dist-info/WHEEL
MSM_PELE-1.1.1.dist-info/metadata.json
MSM_PELE-1.1.1.dist-info/top_level.txt
