Metadata-Version: 2.0
Name: MSM-PELE
Version: 1.1.1
Summary: Monte Carlo Protein Energy Landscape Exploration (PELE) coupled with Markov State Model (MSM) analysis with the aim to calculate absolute free energies
Home-page: https://github.com/danielSoler93/MSM_PELE
Author: Daniel Soler, Francesc Gilbert
Author-email: daniel.soler@nostrumbiodiscovery.com
License: UNKNOWN
Platform: UNKNOWN
Classifier: Programming Language :: Python :: 2
Classifier: License :: OSI Approved :: MIT License
Classifier: Operating System :: OS Independent
Requires-Dist: prody (==1.8.1)
Requires-Dist: mdtraj
Requires-Dist: future
Requires-Dist: pyemma
Requires-Dist: msmtools
